odoo/addons/stock_landed_costs_security/README.rst
odoo/addons/stock_landed_costs_security/__init__.py
odoo/addons/stock_landed_costs_security/__manifest__.py
odoo/addons/stock_landed_costs_security/i18n/it.po
odoo/addons/stock_landed_costs_security/i18n/stock_landed_costs_security.pot
odoo/addons/stock_landed_costs_security/readme/CONFIGURE.rst
odoo/addons/stock_landed_costs_security/readme/CONTRIBUTORS.rst
odoo/addons/stock_landed_costs_security/readme/DESCRIPTION.rst
odoo/addons/stock_landed_costs_security/readme/USAGE.rst
odoo/addons/stock_landed_costs_security/security/ir.model.access.csv
odoo/addons/stock_landed_costs_security/security/stock_landed_costs_security.xml
odoo/addons/stock_landed_costs_security/static/description/icon.png
odoo/addons/stock_landed_costs_security/static/description/icon.svg
odoo/addons/stock_landed_costs_security/static/description/index.html
odoo/addons/stock_landed_costs_security/views/stock_landed_costs_view.xml
odoo_addon_stock_landed_costs_security-16.0.1.0.0.2.dist-info/METADATA
odoo_addon_stock_landed_costs_security-16.0.1.0.0.2.dist-info/WHEEL
odoo_addon_stock_landed_costs_security-16.0.1.0.0.2.dist-info/top_level.txt
odoo_addon_stock_landed_costs_security-16.0.1.0.0.2.dist-info/RECORD
